README.txt
setup.py
docs/HISTORY.txt
jarn/__init__.py
jarn.setuptoolsfixer.egg-info/PKG-INFO
jarn.setuptoolsfixer.egg-info/SOURCES.txt
jarn.setuptoolsfixer.egg-info/dependency_links.txt
jarn.setuptoolsfixer.egg-info/entry_points.txt
jarn.setuptoolsfixer.egg-info/namespace_packages.txt
jarn.setuptoolsfixer.egg-info/not-zip-safe
jarn.setuptoolsfixer.egg-info/requires.txt
jarn.setuptoolsfixer.egg-info/top_level.txt
jarn/setuptoolsfixer/__init__.py