Metadata-Version: 1.0
Name: jarn.setuptoolsfixer
Version: 1.0
Summary: UNKNOWN
Home-page: UNKNOWN
Author: Florian Schulze
Author-email: fschulze@jarn.com
License: GPL
Platform: UNKNOWN
Classifier: Programming Language :: Python
Classifier: Topic :: Software Development :: Libraries :: Python Modules
